MANIFEST.in
README.rst
setup.py
CleverCSS2.egg-info/PKG-INFO
CleverCSS2.egg-info/SOURCES.txt
CleverCSS2.egg-info/dependency_links.txt
CleverCSS2.egg-info/top_level.txt
clevercss2/__init__.py
clevercss2/backwards.py
clevercss2/consts.py
clevercss2/ctranslator.py
clevercss2/errors.py
clevercss2/grammar.py
clevercss2/translator.py
clevercss2/values.py
tests/__init__.py
tests/ccss_to_css.py
tests/color_convert.py
tests/magictest.py
tests/minify.py
tests/one_liners.py
tests/parsing.py
tests/spritemap_test.py
tests/tokenize_.py