Metadata-Version: 1.0
Name: CleverCSS2
Version: 0.5
Summary: python inspired sass-like css preprocessor
Home-page: http://sandbox.pocoo.org/clevercss/
Author: Jared Forsyth
Author-email: jared@jaredforsyth.com
License: UNKNOWN
Download-URL: http://github.com/jabapyth/clevercss2
Platform: UNKNOWN
Classifier: License :: OSI Approved :: BSD License
Classifier: Programming Language :: Python
